MLChatbotAI/Chatbot_AI.py
MLChatbotAI/__init__.py
MLChatbotAI/train_chatbot.py
MLChatbotAI/data/default_intents.json
MLChatbotAI/model/chatbot_model2.h5
MLChatbotAI/model/classes.pkl
MLChatbotAI/model/words.pkl
mlchatbotai-0.10.2.dist-info/METADATA
mlchatbotai-0.10.2.dist-info/WHEEL
mlchatbotai-0.10.2.dist-info/top_level.txt
mlchatbotai-0.10.2.dist-info/RECORD
