Metadata-Version: 2.1
Name: mlchatbotai
Version: 0.10.2
Summary: A simple AI chatbot package
Home-page: https://github.com/ShibamDas007/MLChatbotAI
Author: Shibam Das
Author-email: shibomdas121@gmail.com
Classifier: Programming Language :: Python :: 3
Classifier: License :: OSI Approved :: MIT License
Classifier: Operating System :: OS Independent
Requires-Python: >=3.6
Requires-Dist: numpy
Requires-Dist: nltk
Requires-Dist: keras
Requires-Dist: tensorflow
Requires-Dist: pyttsx3
